[
  {
    "head": "org.springframework.util.unit.DataSizeTests",
    "headType": "class",
    "relation": "haveMethod",
    "tail": "org.springframework.util.unit.DataSizeTests#ofKilobytesToKilobytes()",
    "tailType": "method"
  },
  {
    "head": "org.springframework.util.unit.DataSizeTests#ofKilobytesToKilobytes()",
    "headType": "method",
    "relation": "use",
    "tail": "@Test",
    "tailType": "annotation"
  },
  {
    "head": "org.springframework.util.unit.DataSizeTests#ofKilobytesToMegabytes()",
    "headType": "method",
    "relation": "provide",
    "tail": "@Test\r\nvoid ofKilobytesToMegabytes() {\r\n    assertThat(DataSize.ofKilobytes(1024).toMegabytes()).isEqualTo(1);\r\n}",
    "tailType": "method_code"
  },
  {
    "head": "org.springframework.util.unit.DataSizeTests",
    "headType": "class",
    "relation": "haveMethod",
    "tail": "org.springframework.util.unit.DataSizeTests#ofKilobytesToMegabytes()",
    "tailType": "method"
  },
  {
    "head": "org.springframework.util.unit.DataSizeTests#ofKilobytesToMegabytes()",
    "headType": "method",
    "relation": "use",
    "tail": "@Test",
    "tailType": "annotation"
  },
  {
    "head": "org.springframework.util.unit.DataSizeTests#ofMegabytesToMegabytes()",
    "headType": "method",
    "relation": "provide",
    "tail": "@Test\r\nvoid ofMegabytesToMegabytes() {\r\n    assertThat(DataSize.ofMegabytes(1024).toMegabytes()).isEqualTo(1024);\r\n}",
    "tailType": "method_code"
  },
  {
    "head": "org.springframework.util.unit.DataSizeTests",
    "headType": "class",
    "relation": "haveMethod",
    "tail": "org.springframework.util.unit.DataSizeTests#ofMegabytesToMegabytes()",
    "tailType": "method"
  },
  {
    "head": "org.springframework.util.unit.DataSizeTests#ofMegabytesToMegabytes()",
    "headType": "method",
    "relation": "use",
    "tail": "@Test",
    "tailType": "annotation"
  },
  {
    "head": "org.springframework.util.unit.DataSizeTests#ofMegabytesToGigabytes()",
    "headType": "method",
    "relation": "provide",
    "tail": "@Test\r\nvoid ofMegabytesToGigabytes() {\r\n    assertThat(DataSize.ofMegabytes(2048).toGigabytes()).isEqualTo(2);\r\n}",
    "tailType": "method_code"
  },
  {
    "head": "org.springframework.util.unit.DataSizeTests",
    "headType": "class",
    "relation": "haveMethod",
    "tail": "org.springframework.util.unit.DataSizeTests#ofMegabytesToGigabytes()",
    "tailType": "method"
  },
  {
    "head": "org.springframework.util.unit.DataSizeTests#ofMegabytesToGigabytes()",
    "headType": "method",
    "relation": "use",
    "tail": "@Test",
    "tailType": "annotation"
  },
  {
    "head": "org.springframework.util.unit.DataSizeTests#ofGigabytesToGigabytes()",
    "headType": "method",
    "relation": "provide",
    "tail": "@Test\r\nvoid ofGigabytesToGigabytes() {\r\n    assertThat(DataSize.ofGigabytes(4096).toGigabytes()).isEqualTo(4096);\r\n}",
    "tailType": "method_code"
  },
  {
    "head": "org.springframework.util.unit.DataSizeTests",
    "headType": "class",
    "relation": "haveMethod",
    "tail": "org.springframework.util.unit.DataSizeTests#ofGigabytesToGigabytes()",
    "tailType": "method"
  },
  {
    "head": "org.springframework.util.unit.DataSizeTests#ofGigabytesToGigabytes()",
    "headType": "method",
    "relation": "use",
    "tail": "@Test",
    "tailType": "annotation"
  },
  {
    "head": "org.springframework.util.unit.DataSizeTests#ofGigabytesToTerabytes()",
    "headType": "method",
    "relation": "provide",
    "tail": "@Test\r\nvoid ofGigabytesToTerabytes() {\r\n    assertThat(DataSize.ofGigabytes(4096).toTerabytes()).isEqualTo(4);\r\n}",
    "tailType": "method_code"
  },
  {
    "head": "org.springframework.util.unit.DataSizeTests",
    "headType": "class",
    "relation": "haveMethod",
    "tail": "org.springframework.util.unit.DataSizeTests#ofGigabytesToTerabytes()",
    "tailType": "method"
  },
  {
    "head": "org.springframework.util.unit.DataSizeTests#ofGigabytesToTerabytes()",
    "headType": "method",
    "relation": "use",
    "tail": "@Test",
    "tailType": "annotation"
  },
  {
    "head": "org.springframework.util.unit.DataSizeTests#ofTerabytesToGigabytes()",
    "headType": "method",
    "relation": "provide",
    "tail": "@Test\r\nvoid ofTerabytesToGigabytes() {\r\n    assertThat(DataSize.ofTerabytes(1).toGigabytes()).isEqualTo(1024);\r\n}",
    "tailType": "method_code"
  },
  {
    "head": "org.springframework.util.unit.DataSizeTests",
    "headType": "class",
    "relation": "haveMethod",
    "tail": "org.springframework.util.unit.DataSizeTests#ofTerabytesToGigabytes()",
    "tailType": "method"
  },
  {
    "head": "org.springframework.util.unit.DataSizeTests#ofTerabytesToGigabytes()",
    "headType": "method",
    "relation": "use",
    "tail": "@Test",
    "tailType": "annotation"
  }
]